{
  "post": [
    {
      "user": "aman@gaml.c",
      "data": 12
    },
    {
      "user": "aman@gaml.c",
      "data": 12
    },
    {
      "user": "aman.pal.cs@gmail.com",
      "data": "data a thada"
    },
    {
      "user": "aman.pal.cs@gmail.com",
      "data": "my issue is bad roads"
    },
    {
      "user": "aman.pal.cs@gmail.com",
      "data": "good roads are bad roads\r\n"
    },
    {
      "user": "aman.pal.cs@gmail.com",
      "data": "no issue"
    },
    {
      "user": "aman.pal.cs@gmail.com",
      "data": "its working  perfectly"
    },
    {
      "user": "aman.pal.cs@gmail.com",
      "data": "dfsdfsdf"
    },
    {
      "user": "aman.pal.cs@gmail.com",
      "data": "papa her working"
    },
    {
      "user": "aman.pal.cs@gmail.com",
      "data": "dash too good too"
    },
    {
      "user": "man2g@hotmail.com",
      "data": "anime con"
    },
    {
      "user": "man2g@hotmail.com",
      "data": "anime con"
    },
    {
      "user": "aman.pal.cs@gmail.com",
      "data": "bad roads"
    },
    {
      "user": "aman.pal.cs@gmail.com",
      "data": "values"
    },
    {
      "user": "aman.pal.cs@gmail.com",
      "data": "posting stuff with msg box"
    },
    {
      "user": "aman.pal.cs@gmail.com",
      "data": "posting stuff with msg box"
    },
    {
      "user": "aman.pal.cs@gmail.com",
      "data": "25 nov 2520"
    },
    {
      "user": "aman.pal.cs@gmail.com",
      "data": "asdfdsf"
    },
    {
      "user": "aman.pal.cs@gmail.com",
      "data": "4 18"
    },
    {
      "user": "aman.pal.cs@gmail.com",
      "data": "421"
    },
    {
      "user": "aman.pal.cs@gmail.com",
      "data": "sdfdf"
    },
    {
      "user": "aman.pal.cs@gmail.com",
      "data": "hello"
    },
    {
      "user": "pranjalyadav67a5@gmail.com",
      "data": "garabage dustbin overloded dogs shattering it"
    },
    {
      "user": "pranjalyadav67a5@gmail.com",
      "data": "fdsrcrdcrf"
    },
    {
      "user": ""
    },
    {
      "user": "",
      "data": "sdfdf"
    }
  ]
}